Workbook

Sheet Settings
A1: STYLE & SETTINGS
A2: Style block | B2: bold stylized 2D game icon illustration, single clear focal object, strong readable silhouette, flat cel-shaded color blocks with clean thick inked outline, limited palette of three colors plus one saturated accent, high contrast against a plain solid background, simple geometric shapes, minimal surface detail, no texture
A3: Params | B3: --v 8.1 --ar 5:7 --raw --hd --s 60 --c 0 --no text, letters, words, border, frame, watermark, shadow, gradient, texture, clutter
A4: Sref (optional)
A5: Background tail | B5: plain solid neutral background, centered, front-on
A7: How it works | B7: Final Prompt = Style block + " - " + Subject clause + ", " + Background tail + " " + Params (+ " --sref X" if set). Edit B2/B3 once and every sheet updates. Deadlock-style: bold silhouette, flat color blocks, one accent color, no scene.

Sheet Art Rules
A1: Rule | B1: Detail
A2: One object + one verb | B2: The shape shows the effect so the card reads without its text. Max 2 elements, nothing in the background.
A3: Damage (Sway) | B3: Object moving toward a target: thrust, motion arcs, or an arrow.
A4: Defense (Composure) | B4: Enclosing or blocking shape: shield, closed hand, halo ring.
A5: Draw | B5: A fan of cards, or one card sliding out.
A6: Flock | B6: Repeated identical silhouettes (3 or more).
A7: Accent color | B7: One saturated accent per card (gold for Faith Leader, hot pink for Celebrity, emerald green for Nepo Baby). Everything else stays in the 3-color base.
A8: Avoid | B8: Scenes, crowds of distinct people, textures, glows, soft shadows, fine detail that vanishes at card size.

Sheet Faith Leader
A1: Card | B1: Rarity | C1: Type | D1: Mechanic (from effect list) | E1: Subject clause (editable) | F1: Final Prompt (copy this)
A2: Sermon | B2: Basic | C2: Pressure | D2: Opinion damage; raises all opponents hostility | E2: a single raised open palm thrust forward with three motion arcs, one gold accent | F2: =Settings!$B$2&" - "&E2&", "&Settings!$B$5&" "&Settings!$B$3&IF(Settings!$B$4<>""," --sref "&Settings!$B$4,"")
A3: Pressure | B3: Basic | C3: Pressure | D3: Opinion damage; shifts hostility | E3: one clenched fist pressing down onto a flat slab, one gold accent | F3: =Settings!$B$2&" - "&E3&", "&Settings!$B$5&" "&Settings!$B$3&IF(Settings!$B$4<>""," --sref "&Settings!$B$4,"")
A4: Guilt | B4: Basic | C4: Pressure | D4: Applies Guilt | E4: one heavy weight hanging from a thin chain, one gold accent | F4: =Settings!$B$2&" - "&E4&", "&Settings!$B$5&" "&Settings!$B$3&IF(Settings!$B$4<>""," --sref "&Settings!$B$4,"")
A5: Sow Discord | B5: Basic | C5: Pressure | D5: Opinion damage; applies Doubt | E5: one pointing finger above a single question mark, one gold accent | F5: =Settings!$B$2&" - "&E5&", "&Settings!$B$5&" "&Settings!$B$3&IF(Settings!$B$4<>""," --sref "&Settings!$B$4,"")
A6: Drown out the Haters | B6: Basic | C6: Pressure | D6: Opinion damage; hostility guard | E6: one megaphone with thick sound arcs pushing outward, one gold accent | F6: =Settings!$B$2&" - "&E6&", "&Settings!$B$5&" "&Settings!$B$3&IF(Settings!$B$4<>""," --sref "&Settings!$B$4,"")
A7: Holier Than Thou | B7: Basic | C7: Pressure | D7: Opinion damage | E7: one raised chin and pointing nose above a halo ring, one gold accent | F7: =Settings!$B$2&" - "&E7&", "&Settings!$B$5&" "&Settings!$B$3&IF(Settings!$B$4<>""," --sref "&Settings!$B$4,"")
A8: Impenetrable Belief | B8: Basic | C8: Pressure | D8: Delayed Support | E8: one thick round shield with a cross cut into its face, one gold accent | F8: =Settings!$B$2&" - "&E8&", "&Settings!$B$5&" "&Settings!$B$3&IF(Settings!$B$4<>""," --sref "&Settings!$B$4,"")
A9: Play Favorites | B9: Basic | C9: Pressure | D9: Anger all enemies, calm the focused one | E9: one hand lifting a single silhouette out of a row of identical silhouettes, one gold accent | F9: =Settings!$B$2&" - "&E9&", "&Settings!$B$5&" "&Settings!$B$3&IF(Settings!$B$4<>""," --sref "&Settings!$B$4,"")
A10: Quiet Reflection | B10: Basic | C10: Rhetoric | D10: Delayed Support | E10: one closed eye above a still ripple ring, one gold accent | F10: =Settings!$B$2&" - "&E10&", "&Settings!$B$5&" "&Settings!$B$3&IF(Settings!$B$4<>""," --sref "&Settings!$B$4,"")
A11: Shepherd's Joy | B11: Basic | C11: Rhetoric | D11: Support; grants a turn passive | E11: one shepherd's crook with a single smiling sheep, one gold accent | F11: =Settings!$B$2&" - "&E11&", "&Settings!$B$5&" "&Settings!$B$3&IF(Settings!$B$4<>""," --sref "&Settings!$B$4,"")
A12: Silent Majority | B12: Basic | C12: Rhetoric | D12: Applies Doubt; hostility guard | E12: one closed mouth with a finger pressed to its lips, one gold accent | F12: =Settings!$B$2&" - "&E12&", "&Settings!$B$5&" "&Settings!$B$3&IF(Settings!$B$4<>""," --sref "&Settings!$B$4,"")
A13: Stir the Flock | B13: Basic | C13: Rhetoric | D13: Draw; shifts hostility | E13: one wooden spoon stirring a swirl of identical sheep, one gold accent | F13: =Settings!$B$2&" - "&E13&", "&Settings!$B$5&" "&Settings!$B$3&IF(Settings!$B$4<>""," --sref "&Settings!$B$4,"")
... A51: Scandal | B51: Curse | C51: Scandal | D51: Lose 3 meter every turn | E51: one folded tabloid with two black redaction bars, one crimson accent | F51: =Settings!$B$2&" - "&E51&", "&Settings!$B$5&" "&Settings!$B$3&IF(Settings!$B$4<>""," --sref "&Settings!$B$4,"")

Sheet Celebrity
A1: Card | B1: Rarity | C1: Type | D1: Mechanic (from effect list) | E1: Subject clause (editable) | F1: Final Prompt (copy this)
A2: Autograph | B2: Basic | C2: Pressure | D2: Reduces hostility | E2: one pen signing a looping signature across a single photo card, one hot pink accent | F2: =Settings!$B$2&" - "&E2&", "&Settings!$B$5&" "&Settings!$B$3&IF(Settings!$B$4<>""," --sref "&Settings!$B$4,"")
A3: Hot Take | B3: Basic | C3: Pressure | D3: Sway | E3: one flaming microphone tilted forward with three motion arcs, one hot pink accent | F3: =Settings!$B$2&" - "&E3&", "&Settings!$B$5&" "&Settings!$B$3&IF(Settings!$B$4<>""," --sref "&Settings!$B$4,"")
A4: No Comment | B4: Basic | C4: Pressure | D4: Gain Composure | E4: one raised palm blocking a single microphone, one hot pink accent | F4: =Settings!$B$2&" - "&E4&", "&Settings!$B$5&" "&Settings!$B$3&IF(Settings!$B$4<>""," --sref "&Settings!$B$4,"")
A5: Cash Advance | B5: Basic | C5: Rhetoric | D5: Borrow: energy now, Debt next turn; adds Soundbites | E5: one hand pulling a fat stack of bills out of an ATM slot, one hot pink accent | F5: =Settings!$B$2&" - "&E5&", "&Settings!$B$5&" "&Settings!$B$3&IF(Settings!$B$4<>""," --sref "&Settings!$B$4,"")
A6: Prepared Remarks | B6: Basic | C6: Rhetoric | D6: Composure; adds Soundbites | E6: one stack of cue cards with two cards sliding out, one hot pink accent | F6: =Settings!$B$2&" - "&E6&", "&Settings!$B$5&" "&Settings!$B$3&IF(Settings!$B$4<>""," --sref "&Settings!$B$4,"")
A7: Press Release | B7: Basic | C7: Rhetoric | D7: Composure; gain Glamour | E7: one sealed press envelope inside a thick protective ring, one hot pink accent | F7: =Settings!$B$2&" - "&E7&", "&Settings!$B$5&" "&Settings!$B$3&IF(Settings!$B$4<>""," --sref "&Settings!$B$4,"")
A8: Smile and Wave | B8: Basic | C8: Rhetoric | D8: Composure; gain Glamour | E8: one gloved hand waving above a wide toothy grin, one hot pink accent | F8: =Settings!$B$2&" - "&E8&", "&Settings!$B$5&" "&Settings!$B$3&IF(Settings!$B$4<>""," --sref "&Settings!$B$4,"")
A9: Thumbs Up | B9: Basic | C9: Pressure | D9: Composure; gain Glamour | E9: one thumbs-up hand with a single sparkle, one hot pink accent | F9: =Settings!$B$2&" - "&E9&", "&Settings!$B$5&" "&Settings!$B$3&IF(Settings!$B$4<>""," --sref "&Settings!$B$4,"")
A10: Fine Print | B10: Basic | C10: Policy | D10: Composure equal to Debt; exhausts | E10: one magnifying glass over the tiny bottom lines of a contract, one hot pink accent | F10: =Settings!$B$2&" - "&E10&", "&Settings!$B$5&" "&Settings!$B$3&IF(Settings!$B$4<>""," --sref "&Settings!$B$4,"")
A11: Overdraft | B11: Basic | C11: Policy | D11: Borrow doubled this turn; exhausts | E11: one credit card bending and cracking under a heavy weight, one hot pink accent | F11: =Settings!$B$2&" - "&E11&", "&Settings!$B$5&" "&Settings!$B$3&IF(Settings!$B$4<>""," --sref "&Settings!$B$4,"")
A12: Rain Check | B12: Basic | C12: Policy | D12: Delay Debt settlement; exhausts | E12: one umbrella held over a single unpaid bill, one hot pink accent | F12: =Settings!$B$2&" - "&E12&", "&Settings!$B$5&" "&Settings!$B$3&IF(Settings!$B$4<>""," --sref "&Settings!$B$4,"")
A13: Behind the Podium | B13: Enhanced | C13: Rhetoric | D13: Composure equal to Glamour | E13: one tall podium standing like a shield with a star on its front, one hot pink accent | F13: =Settings!$B$2&" - "&E13&", "&Settings!$B$5&" "&Settings!$B$3&IF(Settings!$B$4<>""," --sref "&Settings!$B$4,"")
... A26: Soundbite | B26: Token | C26: Rhetoric | D26: Sway; exhausts; generated only | E26: one small speech bubble with a bite taken out, flying forward with motion arcs, one hot pink accent | F26: =Settings!$B$2&" - "&E26&", "&Settings!$B$5&" "&Settings!$B$3&IF(Settings!$B$4<>""," --sref "&Settings!$B$4,"")
A27: Advance Booking | B27: Enhanced | C27: Rhetoric | F27: =Settings!$B$2&" - "&E27&", "&Settings!$B$5&" "&Settings!$B$3&IF(Settings!$B$4<>""," --sref "&Settings!$B$4,"")
A28: Charm Offensive | B28: Rare | C28: Pressure | F28: =Settings!$B$2&" - "&E28&", "&Settings!$B$5&" "&Settings!$B$3&IF(Settings!$B$4<>""," --sref "&Settings!$B$4,"")
A29: Disarming Charm | B29: Enhanced | C29: Rhetoric | F29: =Settings!$B$2&" - "&E29&", "&Settings!$B$5&" "&Settings!$B$3&IF(Settings!$B$4<>""," --sref "&Settings!$B$4,"")
A30: Iconic Line | B30: Enhanced | C30: Rhetoric | F30: =Settings!$B$2&" - "&E30&", "&Settings!$B$5&" "&Settings!$B$3&IF(Settings!$B$4<>""," --sref "&Settings!$B$4,"")
A31: Media Training | B31: Enhanced | C31: Policy | F31: =Settings!$B$2&" - "&E31&", "&Settings!$B$5&" "&Settings!$B$3&IF(Settings!$B$4<>""," --sref "&Settings!$B$4,"")
A32: Movie Quote | B32: Token | C32: Rhetoric | F32: =Settings!$B$2&" - "&E32&", "&Settings!$B$5&" "&Settings!$B$3&IF(Settings!$B$4<>""," --sref "&Settings!$B$4,"")
A33: Never Meet Your Heroes | B33: Enhanced | C33: Rhetoric | F33: =Settings!$B$2&" - "&E33&", "&Settings!$B$5&" "&Settings!$B$3&IF(Settings!$B$4<>""," --sref "&Settings!$B$4,"")
A34: Overpromise | B34: Rare | C34: Rhetoric | F34: =Settings!$B$2&" - "&E34&", "&Settings!$B$5&" "&Settings!$B$3&IF(Settings!$B$4<>""," --sref "&Settings!$B$4,"")
A35: Paid-Off Promises | B35: Enhanced | C35: Rhetoric | F35: =Settings!$B$2&" - "&E35&", "&Settings!$B$5&" "&Settings!$B$3&IF(Settings!$B$4<>""," --sref "&Settings!$B$4,"")
A36: Payment Holiday | B36: Enhanced | C36: Rhetoric | F36: =Settings!$B$2&" - "&E36&", "&Settings!$B$5&" "&Settings!$B$3&IF(Settings!$B$4<>""," --sref "&Settings!$B$4,"")
A37: Second Take | B37: Enhanced | C37: Rhetoric | F37: =Settings!$B$2&" - "&E37&", "&Settings!$B$5&" "&Settings!$B$3&IF(Settings!$B$4<>""," --sref "&Settings!$B$4,"")
A38: Signature Catchphrase | B38: Rare | C38: Policy | F38: =Settings!$B$2&" - "&E38&", "&Settings!$B$5&" "&Settings!$B$3&IF(Settings!$B$4<>""," --sref "&Settings!$B$4,"")
A39: Victim Narrative | B39: Enhanced | C39: Rhetoric | F39: =Settings!$B$2&" - "&E39&", "&Settings!$B$5&" "&Settings!$B$3&IF(Settings!$B$4<>""," --sref "&Settings!$B$4,"")

Sheet Nepo Baby
A1: Card | B1: Rarity | C1: Type | D1: Mechanic (from effect list) | E1: Subject clause (editable) | F1: Final Prompt (copy this)
A2: Daddy's Lawyer | B2: Basic | C2: Pressure | D2: Gain Composure (light) | E2: one leather briefcase raised like a shield, one emerald green accent | F2: =Settings!$B$2&" - "&E2&", "&Settings!$B$5&" "&Settings!$B$3&IF(Settings!$B$4<>""," --sref "&Settings!$B$4,"")
A3: Do-Over | B3: Basic | C3: Pressure | D3: Discard hand, draw that many; raises all hostility | E3: one hand sweeping a fan of cards off a table while a fresh fan slides in, one emerald green accent | F3: =Settings!$B$2&" - "&E3&", "&Settings!$B$5&" "&Settings!$B$3&IF(Settings!$B$4<>""," --sref "&Settings!$B$4,"")
A4: Fast Track | B4: Basic | C4: Pressure | D4: Sway; more if you pulled a card this turn | E4: one golden key card thrusting forward with three motion arcs, one emerald green accent | F4: =Settings!$B$2&" - "&E4&", "&Settings!$B$5&" "&Settings!$B$3&IF(Settings!$B$4<>""," --sref "&Settings!$B$4,"")
A5: Last Season | B5: Basic | C5: Pressure | D5: Sway per card discarded this turn | E5: one last-season designer handbag flung forward with motion arcs, one emerald green accent | F5: =Settings!$B$2&" - "&E5&", "&Settings!$B$5&" "&Settings!$B$3&IF(Settings!$B$4<>""," --sref "&Settings!$B$4,"")
A6: Name Drop | B6: Basic | C6: Pressure | D6: Sway (above baseline) | E6: one heavy business card dropping onto a target with impact lines, one emerald green accent | F6: =Settings!$B$2&" - "&E6&", "&Settings!$B$5&" "&Settings!$B$3&IF(Settings!$B$4<>""," --sref "&Settings!$B$4,"")
A7: Pull Rank | B7: Basic | C7: Pressure | D7: Sway; raises target hostility | E7: one jeweled signet ring pressing down like a stamp with motion arcs, one emerald green accent | F7: =Settings!$B$2&" - "&E7&", "&Settings!$B$5&" "&Settings!$B$3&IF(Settings!$B$4<>""," --sref "&Settings!$B$4,"")
A8: Pull Strings | B8: Basic | C8: Pressure | D8: Draw 2, discard 1 | E8: one hand tugging two marionette strings tied to a single card, one emerald green accent | F8: =Settings!$B$2&" - "&E8&", "&Settings!$B$5&" "&Settings!$B$3&IF(Settings!$B$4<>""," --sref "&Settings!$B$4,"")
A9: Skip the Line | B9: Basic | C9: Pressure | D9: Scry 3, draw 1; raises all hostility | E9: one velvet rope unhooked with a single card slipping past it, one emerald green accent | F9: =Settings!$B$2&" - "&E9&", "&Settings!$B$5&" "&Settings!$B$3&IF(Settings!$B$4<>""," --sref "&Settings!$B$4,"")
A10: Apology Tour | B10: Basic | C10: Rhetoric | D10: Reduces target hostility (not below Neutral) | E10: one small white flag waving from a bowed straw hat, one emerald green accent | F10: =Settings!$B$2&" - "&E10&", "&Settings!$B$5&" "&Settings!$B$3&IF(Settings!$B$4<>""," --sref "&Settings!$B$4,"")
A11: Blow the Allowance | B11: Basic | C11: Rhetoric | D11: Burn a card, play it free; Sway equal to its cost | E11: one wad of bills bursting into flame as it flies forward, one emerald green accent | F11: =Settings!$B$2&" - "&E11&", "&Settings!$B$5&" "&Settings!$B$3&IF(Settings!$B$4<>""," --sref "&Settings!$B$4,"")
A12: I Know You Are But What Am I | B12: Basic | C12: Rhetoric | D12: First Opinion hit through Composure this turn returns as Sway | E12: one hand mirror bouncing a single arrow back the way it came, one emerald green accent | F12: =Settings!$B$2&" - "&E12&", "&Settings!$B$5&" "&Settings!$B$3&IF(Settings!$B$4<>""," --sref "&Settings!$B$4,"")
A13: I Know a Guy | B13: Basic | C13: Rhetoric | D13: Return a played Rhetoric card from discard | E13: one phone with a single card sliding up out of its screen, one emerald green accent | F13: =Settings!$B$2&" - "&E13&", "&Settings!$B$5&" "&Settings!$B$3&IF(Settings!$B$4<>""," --sref "&Settings!$B$4,"")
... A43: Trust Fund | B43: Rare | C43: Policy | D43: Passive: Rhetoric replays give energy; raises all hostility | E43: one gold-trimmed piggy bank pouring out coins, one emerald green accent | F43: =Settings!$B$2&" - "&E43&", "&Settings!$B$5&" "&Settings!$B$3&IF(Settings!$B$4<>""," --sref "&Settings!$B$4,"")
